SynthGen.py
synthgen-0.1.1.dist-info/LICENSE.txt
synthgen-0.1.1.dist-info/METADATA
synthgen-0.1.1.dist-info/WHEEL
synthgen-0.1.1.dist-info/RECORD
