Metadata-Version: 2.1
Name: synthgen
Version: 0.1.1
Summary: Generate strings according to specified characteristics
License: MIT
Author: Joseph Lam
Author-email: joseph.lam.18@ucl.ac.uk
Requires-Python: >=3.10,<4.0
Classifier: License :: OSI Approved :: MIT License
Classifier: Programming Language :: Python :: 3
Classifier: Programming Language :: Python :: 3.10
Classifier: Programming Language :: Python :: 3.11
Requires-Dist: numpy (==1.26.3)
